{
  "type": "usefulmagic:altar_recipe",
  "output": {
    "id": "usefulmagic:magic_axe",
    "count": 1
  },
  "data": {
    "0": {
      "item": "minecraft:diamond"
    },
    "1": {
      "item": "minecraft:netherite_ingot"
    },
    "2": {
      "item": "minecraft:diamond"
    },
    "3": {
      "item": "minecraft:amethyst_shard"
    },
    "4": {
      "item": "minecraft:diamond"
    },
    "5": {
      "item": "minecraft:netherite_ingot"
    },
    "6": {
      "item": "minecraft:diamond"
    },
    "7": {
      "item": "minecraft:amethyst_shard"
    }
  },
  "center": {
    "item": "minecraft:diamond_axe"
  },
  "mana_need": 15000,
  "tick": 1000
}